refurb/__init__.py
refurb/__main__.py
refurb/checks/__init__.py
refurb/checks/builtin/__init__.py
refurb/checks/builtin/list_extend.py
refurb/checks/builtin/no_del.py
refurb/checks/builtin/no_ignored_dict_items.py
refurb/checks/builtin/no_ignored_enumerate.py
refurb/checks/builtin/no_is_type_none.py
refurb/checks/builtin/no_isinstance_type_none.py
refurb/checks/builtin/no_set_for_loop.py
refurb/checks/builtin/no_slice_copy.py
refurb/checks/builtin/no_sorted_min_max.py
refurb/checks/builtin/print.py
refurb/checks/builtin/set_discard.py
refurb/checks/builtin/simplify_comprehension.py
refurb/checks/builtin/simplify_global_and_nonlocal.py
refurb/checks/builtin/use_bit_count.py
refurb/checks/builtin/use_int_base_zero.py
refurb/checks/builtin/use_isinstance_tuple.py
refurb/checks/builtin/use_max.py
refurb/checks/builtin/writelines.py
refurb/checks/collections/__init__.py
refurb/checks/collections/no_subclass_builtin.py
refurb/checks/common.py
refurb/checks/contextlib/__init__.py
refurb/checks/contextlib/with_suppress.py
refurb/checks/datetime/__init__.py
refurb/checks/datetime/simplify_fromisoformat.py
refurb/checks/datetime/unreliable_utc_usage.py
refurb/checks/decimal/__init__.py
refurb/checks/decimal/simplify_ctor.py
refurb/checks/flow/__init__.py
refurb/checks/flow/no_trailing_continue.py
refurb/checks/flow/no_trailing_return.py
refurb/checks/flow/no_with_assign.py
refurb/checks/flow/simplify_return.py
refurb/checks/function/__init__.py
refurb/checks/function/use_implicit_default.py
refurb/checks/functools/__init__.py
refurb/checks/functools/use_cache.py
refurb/checks/hashlib/__init__.py
refurb/checks/hashlib/simplify_ctor.py
refurb/checks/hashlib/use_hexdigest.py
refurb/checks/iterable/__init__.py
refurb/checks/iterable/implicit_readlines.py
refurb/checks/iterable/in_tuple.py
refurb/checks/iterable/no_single_item_in.py
refurb/checks/itertools/__init__.py
refurb/checks/itertools/use_chain_from_iterable.py
refurb/checks/itertools/use_starmap.py
refurb-2.2.0.dist-info/METADATA
refurb-2.2.0.dist-info/WHEEL
refurb-2.2.0.dist-info/entry_points.txt
refurb-2.2.0.dist-info/licenses/LICENSE
refurb-2.2.0.dist-info/RECORD
