Metadata-Version: 2.4
Name: refurb
Version: 2.2.0
Summary: A tool for refurbishing and modernizing Python codebases
License: GPL-3.0-only
License-File: LICENSE
Author: dosisod
Requires-Python: >=3.10
Classifier: Development Status :: 5 - Production/Stable
Classifier: Environment :: Console
Classifier: Intended Audience :: Developers
Classifier: License :: OSI Approved :: GNU General Public License v3 (GPLv3)
Classifier: Programming Language :: Python :: 3
Classifier: Programming Language :: Python :: 3.10
Classifier: Programming Language :: Python :: 3.11
Classifier: Programming Language :: Python :: 3.12
Classifier: Programming Language :: Python :: 3.13
Classifier: Programming Language :: Python :: 3.14
Classifier: Topic :: Software Development :: Testing
Classifier: Typing :: Typed
Requires-Dist: mypy (>=1.10.0,!=1.11.0)
Requires-Dist: tomli (>=2.0.1,<3.0.0) ; python_version < "3.11"
Project-URL: Repository, https://github.com/dosisod/refurb
